{"nodes": [{"id": "home_nas_ag_forge_physis_memory_wiki_md", "label": "\ud53c\uc9c0\uc218_\uc0ac\uba85_\uc120\uc5b8.md", "file_type": "document", "source_file": "/home/nas/AG-Forge/physis_memory/wiki/\ud53c\uc9c0\uc218_\uc0ac\uba85_\uc120\uc5b8.md", "source_location": "L1"}, {"id": "wiki", "label": "\ud53c\uc9c0\uc218_\uc0ac\uba85_\uc120\uc5b8", "file_type": "document", "source_file": "/home/nas/AG-Forge/physis_memory/wiki/\ud53c\uc9c0\uc218_\uc0ac\uba85_\uc120\uc5b8.md", "source_location": "L9"}, {"id": "wiki_14", "label": "\ud53c\uc9c0\uc218\uac00 \uc874\uc7ac\ud558\ub294 \uc774\uc720", "file_type": "document", "source_file": "/home/nas/AG-Forge/physis_memory/wiki/\ud53c\uc9c0\uc218_\uc0ac\uba85_\uc120\uc5b8.md", "source_location": "L14"}, {"id": "wiki_20", "label": "\ud53c\uc9c0\uc218\uc758 \ubcf8\uc9c8", "file_type": "document", "source_file": "/home/nas/AG-Forge/physis_memory/wiki/\ud53c\uc9c0\uc218_\uc0ac\uba85_\uc120\uc5b8.md", "source_location": "L20"}, {"id": "wiki_25", "label": "\ud53c\uc9c0\uc218\uac00 \ud574\uc57c \ud558\ub294 \uac83", "file_type": "document", "source_file": "/home/nas/AG-Forge/physis_memory/wiki/\ud53c\uc9c0\uc218_\uc0ac\uba85_\uc120\uc5b8.md", "source_location": "L25"}, {"id": "wiki_31", "label": "\ud53c\uc9c0\uc218\uac00 \ud558\uba74 \uc548 \ub418\ub294 \uac83", "file_type": "document", "source_file": "/home/nas/AG-Forge/physis_memory/wiki/\ud53c\uc9c0\uc218_\uc0ac\uba85_\uc120\uc5b8.md", "source_location": "L31"}, {"id": "wiki_36", "label": "\ud575\uc2ec \uba85\uc5b8 (\ubc29\ubd80\uc7a5 \uce59\ub839)", "file_type": "document", "source_file": "/home/nas/AG-Forge/physis_memory/wiki/\ud53c\uc9c0\uc218_\uc0ac\uba85_\uc120\uc5b8.md", "source_location": "L36"}, {"id": "wiki_43", "label": "\uc5f0\uacb0", "file_type": "document", "source_file": "/home/nas/AG-Forge/physis_memory/wiki/\ud53c\uc9c0\uc218_\uc0ac\uba85_\uc120\uc5b8.md", "source_location": "L43"}], "edges": [{"source": "home_nas_ag_forge_physis_memory_wiki_md", "target": "wiki", "relation": "contains", "confidence": "EXTRACTED", "source_file": "/home/nas/AG-Forge/physis_memory/wiki/\ud53c\uc9c0\uc218_\uc0ac\uba85_\uc120\uc5b8.md", "source_location": "L9", "weight": 1.0}, {"source": "wiki", "target": "wiki_14", "relation": "contains", "confidence": "EXTRACTED", "source_file": "/home/nas/AG-Forge/physis_memory/wiki/\ud53c\uc9c0\uc218_\uc0ac\uba85_\uc120\uc5b8.md", "source_location": "L14", "weight": 1.0}, {"source": "wiki", "target": "wiki_20", "relation": "contains", "confidence": "EXTRACTED", "source_file": "/home/nas/AG-Forge/physis_memory/wiki/\ud53c\uc9c0\uc218_\uc0ac\uba85_\uc120\uc5b8.md", "source_location": "L20", "weight": 1.0}, {"source": "wiki", "target": "wiki_25", "relation": "contains", "confidence": "EXTRACTED", "source_file": "/home/nas/AG-Forge/physis_memory/wiki/\ud53c\uc9c0\uc218_\uc0ac\uba85_\uc120\uc5b8.md", "source_location": "L25", "weight": 1.0}, {"source": "wiki", "target": "wiki_31", "relation": "contains", "confidence": "EXTRACTED", "source_file": "/home/nas/AG-Forge/physis_memory/wiki/\ud53c\uc9c0\uc218_\uc0ac\uba85_\uc120\uc5b8.md", "source_location": "L31", "weight": 1.0}, {"source": "wiki", "target": "wiki_36", "relation": "contains", "confidence": "EXTRACTED", "source_file": "/home/nas/AG-Forge/physis_memory/wiki/\ud53c\uc9c0\uc218_\uc0ac\uba85_\uc120\uc5b8.md", "source_location": "L36", "weight": 1.0}, {"source": "wiki", "target": "wiki_43", "relation": "contains", "confidence": "EXTRACTED", "source_file": "/home/nas/AG-Forge/physis_memory/wiki/\ud53c\uc9c0\uc218_\uc0ac\uba85_\uc120\uc5b8.md", "source_location": "L43", "weight": 1.0}], "input_tokens": 0, "output_tokens": 0}
